{
	"module": "Main",
	"types": [
		{
			"name": "Lobby",
			"struct": [
				{
					"name": "id",
					"type": "U64"
				},
				{
					"name": "player_count",
					"type": "U32"
				}
			],
			"table_names": [
				"lobby"
			],
			"table_name": "lobby",
			"primary_key": 0,
			"primary_key_name": "id",
			"is_public": [
				true
			]
		},
		{
			"name": "Vector2",
			"gd_native": true,
			"struct": [
				{
					"name": "x",
					"type": "F32"
				},
				{
					"name": "y",
					"type": "F32"
				}
			]
		},
		{
			"name": "Vector3",
			"gd_native": true,
			"struct": [
				{
					"name": "x",
					"type": "F32"
				},
				{
					"name": "y",
					"type": "F32"
				},
				{
					"name": "z",
					"type": "F32"
				}
			]
		},
		{
			"name": "Message",
			"struct": [
				{
					"name": "int_value",
					"type": "U8"
				},
				{
					"name": "string_value",
					"type": "String"
				},
				{
					"name": "int_vec",
					"nested_type": [
						"Array"
					],
					"is_array": true,
					"type": "U8"
				},
				{
					"name": "string_vec",
					"nested_type": [
						"Array"
					],
					"is_array": true,
					"type": "String"
				},
				{
					"name": "test_option",
					"nested_type": [
						"Option"
					],
					"is_option": true,
					"type": "String"
				},
				{
					"name": "test_option_vec",
					"nested_type": [
						"Option",
						"Array"
					],
					"is_option": true,
					"is_array_inside_option": true,
					"type": "String"
				},
				{
					"name": "test_inner",
					"nested_type": [
						"Option"
					],
					"is_option": true,
					"type": "Damage"
				}
			]
		},
		{
			"name": "Damage",
			"struct": [
				{
					"name": "amount",
					"type": "U32"
				},
				{
					"name": "source",
					"type": "__identity__"
				},
				{
					"name": "int_vec",
					"nested_type": [
						"Array"
					],
					"is_array": true,
					"type": "U8"
				}
			]
		},
		{
			"name": "User",
			"struct": [
				{
					"name": "identity",
					"type": "__identity__"
				},
				{
					"name": "online",
					"type": "Bool"
				},
				{
					"name": "lobby_id",
					"type": "U64"
				},
				{
					"name": "damage",
					"type": "Damage"
				},
				{
					"name": "test_option_string",
					"nested_type": [
						"Option",
						"Array"
					],
					"is_option": true,
					"is_array_inside_option": true,
					"type": "String"
				},
				{
					"name": "test_option_message",
					"nested_type": [
						"Option"
					],
					"is_option": true,
					"type": "Message"
				}
			],
			"table_names": [
				"user",
				"user_next"
			],
			"table_name": "user_next",
			"primary_key": 0,
			"primary_key_name": "identity",
			"is_public": [
				true,
				true
			]
		},
		{
			"name": "UserData",
			"struct": [
				{
					"name": "identity",
					"type": "__identity__"
				},
				{
					"name": "online",
					"type": "Bool"
				},
				{
					"name": "name",
					"type": "String"
				},
				{
					"name": "lobby_id",
					"type": "U64"
				},
				{
					"name": "color",
					"type": "Color"
				},
				{
					"name": "test_vec",
					"nested_type": [
						"Array"
					],
					"is_array": true,
					"type": "String"
				},
				{
					"name": "test_bytes_array",
					"nested_type": [
						"Array"
					],
					"is_array": true,
					"type": "U8"
				},
				{
					"name": "last_position",
					"type": "Vector3"
				},
				{
					"name": "direction",
					"type": "Vector2"
				},
				{
					"name": "player_speed",
					"type": "F32"
				},
				{
					"name": "last_update",
					"type": "__timestamp_micros_since_unix_epoch__"
				}
			],
			"table_names": [
				"user_data",
				"user_data_hidden"
			],
			"table_name": "user_data_hidden",
			"primary_key": 0,
			"primary_key_name": "identity",
			"is_public": [
				true,
				false
			]
		},
		{
			"name": "Color",
			"gd_native": true,
			"struct": [
				{
					"name": "r",
					"type": "F32"
				},
				{
					"name": "g",
					"type": "F32"
				},
				{
					"name": "b",
					"type": "F32"
				},
				{
					"name": "a",
					"type": "F32"
				}
			]
		}
	],
	"reducers": [
		{
			"name": "change_color_random",
			"params": []
		},
		{
			"name": "move_user",
			"params": [
				{
					"name": "new_input",
					"type": "Vector2"
				},
				{
					"name": "global_position",
					"type": "Vector3"
				}
			]
		},
		{
			"name": "save_my_bytes",
			"params": [
				{
					"name": "bytes",
					"nested_type": [
						"Array"
					],
					"is_array": true,
					"type": "U8"
				}
			]
		},
		{
			"name": "test_option_single",
			"params": [
				{
					"name": "option",
					"nested_type": [
						"Option"
					],
					"is_option": true,
					"type": "String"
				}
			]
		},
		{
			"name": "test_option_vec",
			"params": [
				{
					"name": "option",
					"nested_type": [
						"Option",
						"Array"
					],
					"is_option": true,
					"is_array_inside_option": true,
					"type": "String"
				}
			]
		},
		{
			"name": "test_struct",
			"params": [
				{
					"name": "message",
					"type": "Message"
				}
			]
		}
	],
	"tables": [
		{
			"name": "lobby",
			"type_idx": 0,
			"primary_key": 0,
			"primary_key_name": "id",
			"unique_indexes": [
				{
					"name": "id",
					"type": "U64",
					"constraint_name": "lobby_id_key"
				}
			],
			"is_public": true
		},
		{
			"name": "user",
			"type_idx": 5,
			"primary_key": 0,
			"primary_key_name": "identity",
			"unique_indexes": [
				{
					"name": "identity",
					"type": "__identity__",
					"constraint_name": "user_identity_key"
				}
			],
			"is_public": true
		},
		{
			"name": "user_data",
			"type_idx": 6,
			"primary_key": 0,
			"primary_key_name": "identity",
			"unique_indexes": [
				{
					"name": "identity",
					"type": "__identity__",
					"constraint_name": "user_data_identity_key"
				}
			],
			"is_public": true
		},
		{
			"name": "user_data_hidden",
			"type_idx": 6,
			"primary_key": 0,
			"primary_key_name": "identity",
			"unique_indexes": [
				{
					"name": "identity",
					"type": "__identity__",
					"constraint_name": "user_data_hidden_identity_key"
				}
			],
			"is_public": false
		},
		{
			"name": "user_next",
			"type_idx": 5,
			"primary_key": 0,
			"primary_key_name": "identity",
			"unique_indexes": [
				{
					"name": "identity",
					"type": "__identity__",
					"constraint_name": "user_next_identity_key"
				}
			],
			"is_public": true
		}
	],
	"type_map": {
		"__identity__": "PackedByteArray",
		"__connection_id__": "PackedByteArray",
		"__timestamp_micros_since_unix_epoch__": "int",
		"__time_duration_micros__": "int",
		"I8": "int",
		"I16": "int",
		"I32": "int",
		"I64": "int",
		"U8": "int",
		"U16": "int",
		"U32": "int",
		"U64": "int",
		"F32": "float",
		"F64": "float",
		"String": "String",
		"Vector4": "Vector4",
		"Vector4I": "Vector4i",
		"Vector3": "Vector3",
		"Vector3I": "Vector3i",
		"Vector2": "Vector2",
		"Vector2I": "Vector2i",
		"Plane": "Plane",
		"Color": "Color",
		"Quaternion": "Quaternion",
		"Bool": "bool",
		"Nil": "null",
		"Lobby": "MainLobby",
		"Message": "MainMessage",
		"Damage": "MainDamage",
		"User": "MainUser",
		"UserData": "MainUserData"
	},
	"meta_type_map": {
		"I8": "i8",
		"I16": "i16",
		"I32": "i32",
		"I64": "i64",
		"U8": "u8",
		"U16": "u16",
		"U32": "u32",
		"U64": "u64",
		"F32": "f32",
		"F64": "f64",
		"String": "string",
		"Bool": "bool",
		"Nil": "nil",
		"__identity__": "identity",
		"__connection_id__": "connection_id",
		"__timestamp_micros_since_unix_epoch__": "i64",
		"__time_duration_micros__": "i64",
		"Lobby": "MainLobby",
		"Message": "MainMessage",
		"Damage": "MainDamage",
		"User": "MainUser",
		"UserData": "MainUserData"
	},
	"typespace": [
		{
			"Product": {
				"elements": [
					{
						"name": {
							"some": "id"
						},
						"algebraic_type": {
							"U64": []
						}
					},
					{
						"name": {
							"some": "player_count"
						},
						"algebraic_type": {
							"U32": []
						}
					}
				]
			}
		},
		{
			"Product": {
				"elements": [
					{
						"name": {
							"some": "x"
						},
						"algebraic_type": {
							"F32": []
						}
					},
					{
						"name": {
							"some": "y"
						},
						"algebraic_type": {
							"F32": []
						}
					}
				]
			}
		},
		{
			"Product": {
				"elements": [
					{
						"name": {
							"some": "x"
						},
						"algebraic_type": {
							"F32": []
						}
					},
					{
						"name": {
							"some": "y"
						},
						"algebraic_type": {
							"F32": []
						}
					},
					{
						"name": {
							"some": "z"
						},
						"algebraic_type": {
							"F32": []
						}
					}
				]
			}
		},
		{
			"Product": {
				"elements": [
					{
						"name": {
							"some": "int_value"
						},
						"algebraic_type": {
							"U8": []
						}
					},
					{
						"name": {
							"some": "string_value"
						},
						"algebraic_type": {
							"String": []
						}
					},
					{
						"name": {
							"some": "int_vec"
						},
						"algebraic_type": {
							"Array": {
								"U8": []
							}
						}
					},
					{
						"name": {
							"some": "string_vec"
						},
						"algebraic_type": {
							"Array": {
								"String": []
							}
						}
					},
					{
						"name": {
							"some": "test_option"
						},
						"algebraic_type": {
							"Sum": {
								"variants": [
									{
										"name": {
											"some": "some"
										},
										"algebraic_type": {
											"String": []
										}
									},
									{
										"name": {
											"some": "none"
										},
										"algebraic_type": {
											"Product": {
												"elements": []
											}
										}
									}
								]
							}
						}
					},
					{
						"name": {
							"some": "test_option_vec"
						},
						"algebraic_type": {
							"Sum": {
								"variants": [
									{
										"name": {
											"some": "some"
										},
										"algebraic_type": {
											"Array": {
												"String": []
											}
										}
									},
									{
										"name": {
											"some": "none"
										},
										"algebraic_type": {
											"Product": {
												"elements": []
											}
										}
									}
								]
							}
						}
					},
					{
						"name": {
							"some": "test_inner"
						},
						"algebraic_type": {
							"Sum": {
								"variants": [
									{
										"name": {
											"some": "some"
										},
										"algebraic_type": {
											"Ref": 4.0
										}
									},
									{
										"name": {
											"some": "none"
										},
										"algebraic_type": {
											"Product": {
												"elements": []
											}
										}
									}
								]
							}
						}
					}
				]
			}
		},
		{
			"Product": {
				"elements": [
					{
						"name": {
							"some": "amount"
						},
						"algebraic_type": {
							"U32": []
						}
					},
					{
						"name": {
							"some": "source"
						},
						"algebraic_type": {
							"Product": {
								"elements": [
									{
										"name": {
											"some": "__identity__"
										},
										"algebraic_type": {
											"U256": []
										}
									}
								]
							}
						}
					},
					{
						"name": {
							"some": "int_vec"
						},
						"algebraic_type": {
							"Array": {
								"U8": []
							}
						}
					}
				]
			}
		},
		{
			"Product": {
				"elements": [
					{
						"name": {
							"some": "identity"
						},
						"algebraic_type": {
							"Product": {
								"elements": [
									{
										"name": {
											"some": "__identity__"
										},
										"algebraic_type": {
											"U256": []
										}
									}
								]
							}
						}
					},
					{
						"name": {
							"some": "online"
						},
						"algebraic_type": {
							"Bool": []
						}
					},
					{
						"name": {
							"some": "lobby_id"
						},
						"algebraic_type": {
							"U64": []
						}
					},
					{
						"name": {
							"some": "damage"
						},
						"algebraic_type": {
							"Ref": 4.0
						}
					},
					{
						"name": {
							"some": "test_option_string"
						},
						"algebraic_type": {
							"Sum": {
								"variants": [
									{
										"name": {
											"some": "some"
										},
										"algebraic_type": {
											"Array": {
												"String": []
											}
										}
									},
									{
										"name": {
											"some": "none"
										},
										"algebraic_type": {
											"Product": {
												"elements": []
											}
										}
									}
								]
							}
						}
					},
					{
						"name": {
							"some": "test_option_message"
						},
						"algebraic_type": {
							"Sum": {
								"variants": [
									{
										"name": {
											"some": "some"
										},
										"algebraic_type": {
											"Ref": 3.0
										}
									},
									{
										"name": {
											"some": "none"
										},
										"algebraic_type": {
											"Product": {
												"elements": []
											}
										}
									}
								]
							}
						}
					}
				]
			}
		},
		{
			"Product": {
				"elements": [
					{
						"name": {
							"some": "identity"
						},
						"algebraic_type": {
							"Product": {
								"elements": [
									{
										"name": {
											"some": "__identity__"
										},
										"algebraic_type": {
											"U256": []
										}
									}
								]
							}
						}
					},
					{
						"name": {
							"some": "online"
						},
						"algebraic_type": {
							"Bool": []
						}
					},
					{
						"name": {
							"some": "name"
						},
						"algebraic_type": {
							"String": []
						}
					},
					{
						"name": {
							"some": "lobby_id"
						},
						"algebraic_type": {
							"U64": []
						}
					},
					{
						"name": {
							"some": "color"
						},
						"algebraic_type": {
							"Ref": 7.0
						}
					},
					{
						"name": {
							"some": "test_vec"
						},
						"algebraic_type": {
							"Array": {
								"String": []
							}
						}
					},
					{
						"name": {
							"some": "test_bytes_array"
						},
						"algebraic_type": {
							"Array": {
								"U8": []
							}
						}
					},
					{
						"name": {
							"some": "last_position"
						},
						"algebraic_type": {
							"Ref": 2.0
						}
					},
					{
						"name": {
							"some": "direction"
						},
						"algebraic_type": {
							"Ref": 1.0
						}
					},
					{
						"name": {
							"some": "player_speed"
						},
						"algebraic_type": {
							"F32": []
						}
					},
					{
						"name": {
							"some": "last_update"
						},
						"algebraic_type": {
							"Product": {
								"elements": [
									{
										"name": {
											"some": "__timestamp_micros_since_unix_epoch__"
										},
										"algebraic_type": {
											"I64": []
										}
									}
								]
							}
						}
					}
				]
			}
		},
		{
			"Product": {
				"elements": [
					{
						"name": {
							"some": "r"
						},
						"algebraic_type": {
							"F32": []
						}
					},
					{
						"name": {
							"some": "g"
						},
						"algebraic_type": {
							"F32": []
						}
					},
					{
						"name": {
							"some": "b"
						},
						"algebraic_type": {
							"F32": []
						}
					},
					{
						"name": {
							"some": "a"
						},
						"algebraic_type": {
							"F32": []
						}
					}
				]
			}
		}
	]
}